Metadata-Version: 2.1
Name: morsecco
Version: 0.7.6
Summary: A minimalistic, but mighty programming language
Home-page: https://github.com/Philipp-Sasse/morsecco
Author: Philipp Sasse
Author-email: Philipp.Sasse@sonnenkinder.org
License: BSD 2-clause
Classifier: Development Status :: 3 - Alpha
Classifier: Environment :: Console
Classifier: Intended Audience :: Developers
Classifier: License :: OSI Approved :: BSD License
Classifier: Operating System :: OS Independent
Classifier: Operating System :: MacOS :: MacOS X
Classifier: Operating System :: POSIX :: Linux
Classifier: Programming Language :: Python :: 3
Classifier: Programming Language :: Python :: 3.6
Classifier: Topic :: Software Development :: Interpreters
